nttldict/__init__.py
nttldict-0.0.2.dist-info/LICENSE
nttldict-0.0.2.dist-info/METADATA
nttldict-0.0.2.dist-info/WHEEL
nttldict-0.0.2.dist-info/top_level.txt
nttldict-0.0.2.dist-info/RECORD
