Metadata-Version: 2.1
Name: nttldict
Version: 0.0.2
Summary: Naive TTL dictionary, with optional on-disk persistence
Home-page: UNKNOWN
Author: Carlos Garcia
Author-email: cgarciaarano@yahoo.es
License: UNKNOWN
Platform: UNKNOWN
Requires-Python: >=3.6
